mdp/README.md
mdp/__init__.py
mdp/__main__.py
mdp/cli.py
mdp/collection.py
mdp/conflict.py
mdp/core.py
mdp/document.py
mdp/exceptions.py
mdp/metadata.py
mdp/utils.py
mdp/versioning.py
mdp/commands/README.md
mdp/commands/__init__.py
mdp/commands/diff.py
mdp/commands/doctor.py
mdp/commands/format.py
mdp/commands/lint.py
mdp/commands/summarize.py
mdp/examples/__init__.py
mdp/examples/basic.mdp
mdp/examples/collection_id_types.md
mdp/examples/collections.mdp
mdp/examples/ipfs.mdp
mdp/examples/ipfs_example.py
mdp/examples/relationships.mdp
mdp/lint/__init__.py
mdp/lint/linter.py
mdp/lint/rules.py
mdp/lsp/__init__.py
mdp/lsp/cli.py
mdp/lsp/documents.py
mdp/lsp/features.py
mdp/lsp/protocol.py
mdp/lsp/server.py
mdp/mcp/README.md
mdp/mcp/__init__.py
mdp/mcp/client.py
mdp/mcp/llm_docs.py
mdp/mcp/server.py
mdp/schema/__init__.py
mdp/schema/mdp_schema.json
mdp/schema/mdp_schema_enhanced.json
mdp/schema/validation.py
mdp/tests/README.md
mdp/tests/__init__.py
mdp/tests/run_tests.py
mdp/tests/test_cli.py
mdp/tests/test_collection_id_types.py
mdp/tests/test_commands.py
mdp/tests/test_conflict_resolution.py
mdp/tests/test_core.py
mdp/tests/test_core_additional.py
mdp/tests/test_ipfs_integration.py
mdp/tests/test_main.py
mdp/tests/test_main_additional.py
mdp/tests/test_metadata_extraction.py
mdp/tests/test_relationships.py
mdp/tests/test_user_friendly_api.py
mdp/tests/test_utils.py
mdp/tests/test_versioning.py
mdp_py-0.1.0.dist-info/LICENSE
mdp_py-0.1.0.dist-info/METADATA
mdp_py-0.1.0.dist-info/WHEEL
mdp_py-0.1.0.dist-info/entry_points.txt
mdp_py-0.1.0.dist-info/top_level.txt
mdp_py-0.1.0.dist-info/RECORD
