Metadata-Version: 2.2
Name: mdp-py
Version: 0.1.0
Summary: Markdown Data Package (MDP): A global standard file specification for contextual document management with LLMs
Author-email: MDP Team <contact@markdowndatapackage.org>
License: MIT
Project-URL: repository, https://github.com/greyhaven-ai/mdp
Project-URL: documentation, https://markdowndatapackage.org
Project-URL: issues, https://github.com/greyhaven-ai/mdp/issues
Classifier: Development Status :: 4 - Beta
Classifier: Intended Audience :: Developers
Classifier: Intended Audience :: Information Technology
Classifier: License :: OSI Approved :: MIT License
Classifier: Programming Language :: Python :: 3
Classifier: Programming Language :: Python :: 3.8
Classifier: Programming Language :: Python :: 3.9
Classifier: Programming Language :: Python :: 3.10
Classifier: Programming Language :: Python :: 3.11
Classifier: Programming Language :: Python :: 3.12
Classifier: Topic :: Documentation
Classifier: Topic :: Software Development :: Documentation
Classifier: Topic :: Text Processing :: Markup :: Markdown
Requires-Python: <3.13,>=3.8
License-File: LICENSE
Requires-Dist: pydantic==2.10.6
Requires-Dist: jsonschema
Requires-Dist: pyyaml>=6.0
Requires-Dist: setuptools
Requires-Dist: fastmcp
Requires-Dist: mcp>=1.3.0
Requires-Dist: markdown>=3.4.0
Requires-Dist: python-frontmatter>=1.0.0
Requires-Dist: python-dateutil>=2.8.2
Requires-Dist: pytz>=2023.3
Requires-Dist: requests>=2.28.0
Provides-Extra: dev
Requires-Dist: pytest==8.3.4; extra == "dev"
Requires-Dist: pytest-asyncio==0.25.2; extra == "dev"
Requires-Dist: pytest-cov==6.0.0; extra == "dev"
Requires-Dist: mypy==1.14.1; extra == "dev"
Requires-Dist: ruff>=0.9.5; extra == "dev"
Requires-Dist: deptry>=0.12.0; extra == "dev"
Provides-Extra: lsp
Requires-Dist: pygls>=1.0.0; extra == "lsp"
